promtstd/__main__.py
promtstd/lib_linter.py
promtstd/lib_main.py
promtstd/lib_re.py
promtstd/lib_types.py
promtstd/test/test_main.py
promtstd/test/utils.py
promtstd-1.0.2.dist-info/METADATA
promtstd-1.0.2.dist-info/WHEEL
promtstd-1.0.2.dist-info/RECORD
