Metadata-Version: 2.1
Name: promtstd
Version: 1.0.2
Summary: promtstd robot - универсальный стандарт для хранения и использования промтов в AI. books Основан на Markdown, обеспечивает легкость чтения и структурированность. 
Home-page: https://github.com/denisxab/promtstd
Keywords: стандарт промтов,promtstd,promt,ai,хранение промтов,использование промтов,разработка AI,искусственный интеллект,Markdown,унификация,структурирование,синтаксис,взаимодействие разработчиков,метаинформация,шаблоны,примеры,вспомогательные промты
Author: Denis Kustov
Author-email: pro-progerkustov@yandex.ru
Requires-Python: >=3.9,<4.0
Classifier: Programming Language :: Python :: 3
Classifier: Programming Language :: Python :: 3.9
Classifier: Programming Language :: Python :: 3.10
Classifier: Programming Language :: Python :: 3.11
Project-URL: Repository, https://github.com/denisxab/promtstd
